freyr/__init__.py
freyr/__main__.py
freyr/console.py
freyr/constants.py
freyr/models.py
freyr/responses.py
freyr/settings.py
freyr/utils.py
freyr/database/__init__.py
freyr/database/tables.py
freyr/routers/__init__.py
freyr/routers/api.py
freyr/routers/html.py
freyr-0.3.5.dist-info/METADATA
freyr-0.3.5.dist-info/WHEEL
freyr-0.3.5.dist-info/entry_points.txt
freyr-0.3.5.dist-info/licenses/LICENSE
freyr-0.3.5.dist-info/RECORD
