Metadata-Version: 2.1
Name: freyr
Version: 0.3.5
Summary: Tracks temperature and humidity readings and graphs the results in a web dashboard.
Project-URL: Documentation, https://github.com/Buried-In-Code/Freyr#readme
Project-URL: Issues, https://github.com/Buried-In-Code/Freyr/issues
Project-URL: Source, https://github.com/Buried-In-Code/Freyr
Author-email: BuriedInCode <BuriedInCode@tuta.io>
License: MIT
License-File: LICENSE
Keywords: dht22,fastapi,micropython,pi-pico-w
Classifier: Development Status :: 4 - Beta
Classifier: Intended Audience :: End Users/Desktop
Classifier: License :: OSI Approved :: MIT License
Classifier: Natural Language :: English
Classifier: Operating System :: MacOS
Classifier: Operating System :: Microsoft :: Windows
Classifier: Operating System :: POSIX :: Linux
Classifier: Programming Language :: Python :: 3.11
Classifier: Typing :: Typed
Requires-Python: >=3.11
Requires-Dist: fastapi>=0.104.1
Requires-Dist: jinja2>=3.1.2
Requires-Dist: pony>=0.7.16
Requires-Dist: pydantic>=2.5.1
Requires-Dist: rich>=13.7.0
Requires-Dist: tomli-w>=1.0.0
Requires-Dist: uvicorn>=0.23.2
Provides-Extra: dev
Requires-Dist: pre-commit>=3.5.0; extra == 'dev'
Provides-Extra: postgres
Requires-Dist: psycopg2>=2.9.9; extra == 'postgres'
